nppretty/__init__.py
nppretty/arrayStream.py
nppretty/formatArray.py
nppretty/test/__init__.py
nppretty/test/arrayStream.py
nppretty-1.0.0.dist-info/LICENSE.txt
nppretty-1.0.0.dist-info/METADATA
nppretty-1.0.0.dist-info/WHEEL
nppretty-1.0.0.dist-info/top_level.txt
nppretty-1.0.0.dist-info/RECORD
