Metadata-Version: 2.1
Name: nppretty
Version: 1.0.0
Summary: Pretty printer for numpy arrays.
Home-page: https://github.com/telamonian/nppretty
Author: Max Klein
License: BSD
Keywords: Array,Formatting,Printing,Numpy
Platform: Linux
Platform: Mac OS X
Platform: Windows
Classifier: Intended Audience :: Developers
Classifier: Intended Audience :: Science/Research
Classifier: License :: OSI Approved :: BSD License
Classifier: Programming Language :: Python
Classifier: Programming Language :: Python :: 2.7
Classifier: Programming Language :: Python :: 3
Requires-Dist: numpy
Requires-Dist: six
Provides-Extra: heatmap
Requires-Dist: seaborn; extra == 'heatmap'
